Workbook

Sheet Read Me
B1: Cybersecurity Roles — Estimated Cost of Training
B2: Source data: 'Cybersecurity Roles and Recommended Certification' (Excellog.Biz). Prepared June 2026.
B4: What this workbook does
B5: For every role in the graphic, it sums the cost of ALL the certifications listed next to that role, under two scenarios:
B6: • Exam-only — the minimum to get certified if you self-study (exam/voucher fees + required application fees).
B7: • Training-inclusive — exam plus a typical official or instructor-led training course / bootcamp.
B8: It also shows a 'Most-recognised single credential' per role: a realistic figure if you pursue just one headline cert.
B10: IMPORTANT — read before using the numbers
B11: 1. The certs beside each role are OPTIONS / alternatives, not a required set. Almost nobody earns all of them. The
B12: 'all listed certs' totals are therefore an UPPER BOUND, useful for budgeting a full credential stack — not a typical spend.
B13: For a realistic single-path budget, use the 'Most-recognised single credential' columns on the Summary tab.
B14: 2. GIAC/SANS certs dominate any total: ~$999 for the exam alone, but ~$9,000 once SANS training is included. Roles with
... B25: automatically. To change which certs belong to a role, edit the 'Role–Cert Detail' tab.

Sheet Certification Costs
A1: Certification | B1: Issuing body | C1: Exam-only ($) | D1: Training-incl. ($) | E1: Confidence | F1: Basis / source
A2: CISSP | B2: ISC2 | C2: 749 | D2: 2500 | E2: High | F2: ISC2 exam $749 + $135/yr AMF; training $300-7,000 (web, 2026)
A3: CISM | B3: ISACA | C3: 760 | D3: 1800 | E3: High | F3: ISACA non-member exam $760 + $50 app; official review ~$895 (web, 2026)
A4: CISA | B4: ISACA | C4: 760 | D4: 1700 | E4: High | F4: ISACA non-member exam $760 + $50 app (web, 2026)
A5: CRISC | B5: ISACA | C5: 760 | D5: 1600 | E5: High | F5: ISACA non-member exam $760 + $50 app (web, 2026)
A6: CompTIA Security+ | B6: CompTIA | C6: 425 | D6: 900 | E6: High | F6: Voucher $425; self-study total $600-1,000 (web, 2026)
A7: CompTIA PenTest+ | B7: CompTIA | C7: 425 | D7: 900 | E7: High | F7: Voucher $425 (web, 2026)
A8: CompTIA CySA+ | B8: CompTIA | C8: 425 | D8: 900 | E8: High | F8: Voucher $425 (web, 2026)
A9: CompTIA CASP+ (SecurityX) | B9: CompTIA | C9: 529 | D9: 1200 | E9: High | F9: SecurityX/CASP+ voucher $529 (web, 2026)
A10: CompTIA Secure Software Developer | B10: ISC2 (CSSLP-equiv.) | C10: 599 | D10: 2000 | E10: Low | F10: Ambiguous label; priced as ISC2 CSSLP ~$599 exam (estimate)
A11: CEH | B11: EC-Council | C11: 1199 | D11: 3000 | E11: High | F11: Pearson VUE voucher $1,199 (+$100 app self-study); training $1,900-3,500 (web, 2026)
A12: ECSS | B12: EC-Council | C12: 250 | D12: 800 | E12: Low | F12: Essentials-tier; estimate
A13: CTIA | B13: EC-Council | C13: 450 | D13: 2000 | E13: Medium | F13: EC-Council specialist exam; training bundle (estimate, 2026)
... A45: CDPPE | B45: Unclear | C45: 1000 | D45: 1500 | E45: Very low | F45: Data privacy/protection cert; label unclear (estimate)
A47: Blue cells are editable inputs — change a price and every role total updates.

Sheet Role–Cert Detail
A1: Role | B1: Certification | C1: Exam-only ($) | D1: Training-incl. ($)
A2: Chief Information Security Officer | B2: CISSP | C2: =VLOOKUP(B2,'Certification Costs'!$A:$D,3,FALSE()) -> 749 | D2: =VLOOKUP(B2,'Certification Costs'!$A:$D,4,FALSE()) -> 2500
A3: Chief Information Security Officer | B3: CISM | C3: =VLOOKUP(B3,'Certification Costs'!$A:$D,3,FALSE()) -> 760 | D3: =VLOOKUP(B3,'Certification Costs'!$A:$D,4,FALSE()) -> 1800
A4: Chief Information Security Officer | B4: GSEC (GIAC) | C4: =VLOOKUP(B4,'Certification Costs'!$A:$D,3,FALSE()) -> 999 | D4: =VLOOKUP(B4,'Certification Costs'!$A:$D,4,FALSE()) -> 9000
A5: Information Security Manager | B5: CISSP | C5: =VLOOKUP(B5,'Certification Costs'!$A:$D,3,FALSE()) -> 749 | D5: =VLOOKUP(B5,'Certification Costs'!$A:$D,4,FALSE()) -> 2500
A6: Information Security Manager | B6: CISM | C6: =VLOOKUP(B6,'Certification Costs'!$A:$D,3,FALSE()) -> 760 | D6: =VLOOKUP(B6,'Certification Costs'!$A:$D,4,FALSE()) -> 1800
A7: Information Security Manager | B7: CompTIA Security+ | C7: =VLOOKUP(B7,'Certification Costs'!$A:$D,3,FALSE()) -> 425 | D7: =VLOOKUP(B7,'Certification Costs'!$A:$D,4,FALSE()) -> 900
A8: Cybersecurity Architect | B8: CISSP | C8: =VLOOKUP(B8,'Certification Costs'!$A:$D,3,FALSE()) -> 749 | D8: =VLOOKUP(B8,'Certification Costs'!$A:$D,4,FALSE()) -> 2500
A9: Cybersecurity Architect | B9: CEH | C9: =VLOOKUP(B9,'Certification Costs'!$A:$D,3,FALSE()) -> 1199 | D9: =VLOOKUP(B9,'Certification Costs'!$A:$D,4,FALSE()) -> 3000
A10: Cybersecurity Architect | B10: SANS GIAC (generic) | C10: =VLOOKUP(B10,'Certification Costs'!$A:$D,3,FALSE()) -> 999 | D10: =VLOOKUP(B10,'Certification Costs'!$A:$D,4,FALSE()) -> 9000
A11: Cybersecurity Architect | B11: CISM | C11: =VLOOKUP(B11,'Certification Costs'!$A:$D,3,FALSE()) -> 760 | D11: =VLOOKUP(B11,'Certification Costs'!$A:$D,4,FALSE()) -> 1800
A12: Risk / Compliance Manager | B12: CISSP | C12: =VLOOKUP(B12,'Certification Costs'!$A:$D,3,FALSE()) -> 749 | D12: =VLOOKUP(B12,'Certification Costs'!$A:$D,4,FALSE()) -> 2500
A13: Risk / Compliance Manager | B13: CRISC | C13: =VLOOKUP(B13,'Certification Costs'!$A:$D,3,FALSE()) -> 760 | D13: =VLOOKUP(B13,'Certification Costs'!$A:$D,4,FALSE()) -> 1600
... A95: Privacy Analyst | B95: CDPPE | C95: =VLOOKUP(B95,'Certification Costs'!$A:$D,3,FALSE()) -> 1000 | D95: =VLOOKUP(B95,'Certification Costs'!$A:$D,4,FALSE()) -> 1500

Sheet Summary by Role
A1: Role | B1: Certs listed in graphic | C1: # certs | D1: ALL listed certs: Exam-only ($) | E1: ALL listed certs: Training-incl. ($) | F1: Most-recognised single credential | G1: Single cert: Exam-only ($) | H1: Single cert: Training-incl. ($)
A2: Chief Information Security Officer | B2: CISSP, CISM, GSEC (GIAC) | C2: =COUNTIF('Role–Cert Detail'!$A:$A,A2) -> 3 | D2: =SUMIF('Role–Cert Detail'!$A:$A,A2,'Role–Cert Detail'!$C:$C) -> 2508 | E2: =SUMIF('Role–Cert Detail'!$A:$A,A2,'Role–Cert Detail'!$D:$D) -> 13300 | F2: CISSP | G2: =VLOOKUP(F2,'Certification Costs'!$A:$D,3,FALSE()) -> 749 | H2: =VLOOKUP(F2,'Certification Costs'!$A:$D,4,FALSE()) -> 2500
A3: Information Security Manager | B3: CISSP, CISM, CompTIA Security+ | C3: =COUNTIF('Role–Cert Detail'!$A:$A,A3) -> 3 | D3: =SUMIF('Role–Cert Detail'!$A:$A,A3,'Role–Cert Detail'!$C:$C) -> 1934 | E3: =SUMIF('Role–Cert Detail'!$A:$A,A3,'Role–Cert Detail'!$D:$D) -> 5200 | F3: CISM | G3: =VLOOKUP(F3,'Certification Costs'!$A:$D,3,FALSE()) -> 760 | H3: =VLOOKUP(F3,'Certification Costs'!$A:$D,4,FALSE()) -> 1800
A4: Cybersecurity Architect | B4: CISSP, CEH, SANS GIAC (generic), CISM | C4: =COUNTIF('Role–Cert Detail'!$A:$A,A4) -> 4 | D4: =SUMIF('Role–Cert Detail'!$A:$A,A4,'Role–Cert Detail'!$C:$C) -> 3707 | E4: =SUMIF('Role–Cert Detail'!$A:$A,A4,'Role–Cert Detail'!$D:$D) -> 16300 | F4: CISSP | G4: =VLOOKUP(F4,'Certification Costs'!$A:$D,3,FALSE()) -> 749 | H4: =VLOOKUP(F4,'Certification Costs'!$A:$D,4,FALSE()) -> 2500
A5: Risk / Compliance Manager | B5: CISSP, CRISC, CISA, GSEC (GIAC), CRMP | C5: =COUNTIF('Role–Cert Detail'!$A:$A,A5) -> 5 | D5: =SUMIF('Role–Cert Detail'!$A:$A,A5,'Role–Cert Detail'!$C:$C) -> 3863 | E5: =SUMIF('Role–Cert Detail'!$A:$A,A5,'Role–Cert Detail'!$D:$D) -> 16300 | F5: CRISC | G5: =VLOOKUP(F5,'Certification Costs'!$A:$D,3,FALSE()) -> 760 | H5: =VLOOKUP(F5,'Certification Costs'!$A:$D,4,FALSE()) -> 1600
A6: Cyber Policy Planner | B6: CISSP, CISM, CompTIA CASP+ (SecurityX), GSEC (GIAC), SSCP | C6: =COUNTIF('Role–Cert Detail'!$A:$A,A6) -> 5 | D6: =SUMIF('Role–Cert Detail'!$A:$A,A6,'Role–Cert Detail'!$C:$C) -> 3286 | E6: =SUMIF('Role–Cert Detail'!$A:$A,A6,'Role–Cert Detail'!$D:$D) -> 15400 | F6: CISSP | G6: =VLOOKUP(F6,'Certification Costs'!$A:$D,3,FALSE()) -> 749 | H6: =VLOOKUP(F6,'Certification Costs'!$A:$D,4,FALSE()) -> 2500
A7: Security Awareness Trainer | B7: ECSS, CompTIA Security+ | C7: =COUNTIF('Role–Cert Detail'!$A:$A,A7) -> 2 | D7: =SUMIF('Role–Cert Detail'!$A:$A,A7,'Role–Cert Detail'!$C:$C) -> 675 | E7: =SUMIF('Role–Cert Detail'!$A:$A,A7,'Role–Cert Detail'!$D:$D) -> 1700 | F7: CompTIA Security+ | G7: =VLOOKUP(F7,'Certification Costs'!$A:$D,3,FALSE()) -> 425 | H7: =VLOOKUP(F7,'Certification Costs'!$A:$D,4,FALSE()) -> 900
A8: DevSecOps Engineer | B8: GCSA (GIAC), CDE (DevSecOps), CDP (DevSecOps), CKA, DCA (Docker) | C8: =COUNTIF('Role–Cert Detail'!$A:$A,A8) -> 5 | D8: =SUMIF('Role–Cert Detail'!$A:$A,A8,'Role–Cert Detail'!$C:$C) -> 3338 | E8: =SUMIF('Role–Cert Detail'!$A:$A,A8,'Role–Cert Detail'!$D:$D) -> 11539 | F8: CKA | G8: =VLOOKUP(F8,'Certification Costs'!$A:$D,3,FALSE()) -> 445 | H8: =VLOOKUP(F8,'Certification Costs'!$A:$D,4,FALSE()) -> 645
A9: Cyber Security Consultant | B9: CompTIA Security+, CISSP, CISM, CEH | C9: =COUNTIF('Role–Cert Detail'!$A:$A,A9) -> 4 | D9: =SUMIF('Role–Cert Detail'!$A:$A,A9,'Role–Cert Detail'!$C:$C) -> 3133 | E9: =SUMIF('Role–Cert Detail'!$A:$A,A9,'Role–Cert Detail'!$D:$D) -> 8200 | F9: CISSP | G9: =VLOOKUP(F9,'Certification Costs'!$A:$D,3,FALSE()) -> 749 | H9: =VLOOKUP(F9,'Certification Costs'!$A:$D,4,FALSE()) -> 2500
A10: Information Security Analyst | B10: CompTIA Security+, CEH, CISSP | C10: =COUNTIF('Role–Cert Detail'!$A:$A,A10) -> 3 | D10: =SUMIF('Role–Cert Detail'!$A:$A,A10,'Role–Cert Detail'!$C:$C) -> 2373 | E10: =SUMIF('Role–Cert Detail'!$A:$A,A10,'Role–Cert Detail'!$D:$D) -> 6400 | F10: CompTIA Security+ | G10: =VLOOKUP(F10,'Certification Costs'!$A:$D,3,FALSE()) -> 425 | H10: =VLOOKUP(F10,'Certification Costs'!$A:$D,4,FALSE()) -> 900
A11: Penetration Tester | B11: OSCP, CEH, CompTIA PenTest+, CwPT | C11: =COUNTIF('Role–Cert Detail'!$A:$A,A11) -> 4 | D11: =SUMIF('Role–Cert Detail'!$A:$A,A11,'Role–Cert Detail'!$C:$C) -> 3823 | E11: =SUMIF('Role–Cert Detail'!$A:$A,A11,'Role–Cert Detail'!$D:$D) -> 6649 | F11: OSCP | G11: =VLOOKUP(F11,'Certification Costs'!$A:$D,3,FALSE()) -> 1699 | H11: =VLOOKUP(F11,'Certification Costs'!$A:$D,4,FALSE()) -> 1749
A12: SOC Manager | B12: CISSP, CISM, CSOC, GSOM (GIAC) | C12: =COUNTIF('Role–Cert Detail'!$A:$A,A12) -> 4 | D12: =SUMIF('Role–Cert Detail'!$A:$A,A12,'Role–Cert Detail'!$C:$C) -> 2958 | E12: =SUMIF('Role–Cert Detail'!$A:$A,A12,'Role–Cert Detail'!$D:$D) -> 14800 | F12: CISSP | G12: =VLOOKUP(F12,'Certification Costs'!$A:$D,3,FALSE()) -> 749 | H12: =VLOOKUP(F12,'Certification Costs'!$A:$D,4,FALSE()) -> 2500
A13: SIEM Engineer | B13: CISSP, CISM, CompTIA CySA+, CompTIA CASP+ (SecurityX), CSOM, GDSA (GIAC), GCIA (GIAC) | C13: =COUNTIF('Role–Cert Detail'!$A:$A,A13) -> 7 | D13: =SUMIF('Role–Cert Detail'!$A:$A,A13,'Role–Cert Detail'!$C:$C) -> 4911 | E13: =SUMIF('Role–Cert Detail'!$A:$A,A13,'Role–Cert Detail'!$D:$D) -> 25900 | F13: CompTIA CySA+ | G13: =VLOOKUP(F13,'Certification Costs'!$A:$D,3,FALSE()) -> 425 | H13: =VLOOKUP(F13,'Certification Costs'!$A:$D,4,FALSE()) -> 900
... A25: Privacy Analyst | B25: CIPP, CIPM, CDPO, CIPT, CDPPE | C25: =COUNTIF('Role–Cert Detail'!$A:$A,A25) -> 5 | D25: =SUMIF('Role–Cert Detail'!$A:$A,A25,'Role–Cert Detail'!$C:$C) -> 3650 | E25: =SUMIF('Role–Cert Detail'!$A:$A,A25,'Role–Cert Detail'!$D:$D) -> 6600 | F25: CIPP | G25: =VLOOKUP(F25,'Certification Costs'!$A:$D,3,FALSE()) -> 550 | H25: =VLOOKUP(F25,'Certification Costs'!$A:$D,4,FALSE()) -> 1200
A26: Average across roles | D26: =AVERAGE(D2:D25) -> 2799.0417 | E26: =AVERAGE(E2:E25) -> 10466.167 | G26: =AVERAGE(G2:G25) -> 678.33333 | H26: =AVERAGE(H2:H25) -> 2224.75
A28: Green = pulled from other tabs. 'ALL listed certs' = upper bound (every option). 'Single credential' = realistic one-cert path.
